pocketbase_sdk/__init__.py
pocketbase_sdk/client.py
pocketbase_sdk/services/__init__.py
pocketbase_sdk/services/base_service.py
pocketbase_sdk/services/batch_service.py
pocketbase_sdk/services/collection_service.py
pocketbase_sdk/services/crud_service.py
pocketbase_sdk/services/health_service.py
pocketbase_sdk/services/log_service.py
pocketbase_sdk/services/realtime_service.py
pocketbase_sdk/services/record_service.py
pocketbase_sdk/stores/__init__.py
pocketbase_sdk/stores/async_auth_store.py
pocketbase_sdk/stores/base_auth_store.py
pocketbase_sdk/stores/local_auth_store.py
pocketbase_sdk/utils/__init__.py
pocketbase_sdk/utils/cookie.py
pocketbase_sdk/utils/dtos.py
pocketbase_sdk/utils/exceptions.py
pocketbase_sdk/utils/jwt.py
pocketbase_sdk/utils/options.py
pocketbase_sdk-0.1.2.dist-info/licenses/LICENSE.md
pocketbase_sdk-0.1.2.dist-info/METADATA
pocketbase_sdk-0.1.2.dist-info/WHEEL
pocketbase_sdk-0.1.2.dist-info/top_level.txt
pocketbase_sdk-0.1.2.dist-info/RECORD
