Metadata-Version: 2.4
Name: pocketbase_sdk
Version: 0.1.2
Summary: PocketBase Python SDK - A unofficial Python client library for PocketBase backend
Author-email: PocketBase Python SDK <1154693969@qq.com>
License: MIT
Project-URL: Homepage, https://pocketbase.io
Project-URL: Repository, https://github.com/pocketbase/pocketbase-python-sdk
Project-URL: Documentation, https://pocketbase.io/docs/
Project-URL: Bug Tracker, https://github.com/pocketbase/pocketbase-python-sdk/issues
Keywords: pocketbase,database,backend,api,client,sdk
Classifier: Development Status :: 4 - Beta
Classifier: Intended Audience :: Developers
Classifier: License :: OSI Approved :: MIT License
Classifier: Operating System :: OS Independent
Classifier: Programming Language :: Python :: 3
Classifier: Programming Language :: Python :: 3.8
Classifier: Programming Language :: Python :: 3.9
Classifier: Programming Language :: Python :: 3.10
Classifier: Programming Language :: Python :: 3.11
Classifier: Programming Language :: Python :: 3.12
Classifier: Topic :: Software Development :: Libraries :: Python Modules
Classifier: Topic :: Internet :: WWW/HTTP
Requires-Python: >=3.8
License-File: LICENSE.md
Requires-Dist: aiohttp>=3.8.0
Requires-Dist: websockets>=11.0.0
Provides-Extra: dev
Requires-Dist: pytest>=7.0.0; extra == "dev"
Requires-Dist: pytest-asyncio>=0.21.0; extra == "dev"
Requires-Dist: black>=23.0.0; extra == "dev"
Requires-Dist: flake8>=6.0.0; extra == "dev"
Requires-Dist: mypy>=1.0.0; extra == "dev"
Dynamic: license-file
